tunas2dsdl/__init__.py
tunas2dsdl/__version__.py
tunas2dsdl/cli.py
tunas2dsdl/general/__init__.py
tunas2dsdl/general/classdomain.py
tunas2dsdl/general/samples.py
tunas2dsdl/general/struct.py
tunas2dsdl/general/utils.py
tunas2dsdl/generator/__init__.py
tunas2dsdl/generator/generate.py
tunas2dsdl/io/__init__.py
tunas2dsdl/io/file_client.py
tunas2dsdl/io/fileio.py
tunas2dsdl/parser/__init__.py
tunas2dsdl/parser/base_parse.py
tunas2dsdl/parser/detection_parse.py
tunas2dsdl/parser/keypoint_parse.py
tunas2dsdl/parser/semantic_seg_parse.py
tunas2dsdl-0.1.15.8.dist-info/METADATA
tunas2dsdl-0.1.15.8.dist-info/WHEEL
tunas2dsdl-0.1.15.8.dist-info/entry_points.txt
tunas2dsdl-0.1.15.8.dist-info/top_level.txt
tunas2dsdl-0.1.15.8.dist-info/RECORD
