Metadata-Version: 2.1
Name: tunas2dsdl
Version: 0.1.15.8
Summary: Python SDK for Converting Tunas Format Dataset to DSDL YAML
Author: DSDL team
Author-email: hanxiao@pjlab.org.cn
License: UNKNOWN
Platform: UNKNOWN
Classifier: Programming Language :: Python :: 3.8
Classifier: Programming Language :: Python :: 3.9
Classifier: Programming Language :: Python :: 3.10
Requires-Python: >=3.8
Requires-Dist: click (>=8.1.3)
Requires-Dist: ruamel.yaml (>=0.17.21)
Requires-Dist: tqdm (>=4.64.0)
